{
  "parent": "wilder_horizons:survival/cycles",
  "display": {
    "title": {
      "text": "Hollowed"
    },
    "icon": {
      "item": "wilder_horizons:faded_soul_rose"
    },
    "description": {
      "text": "Harvest a Soul Rose"
    },
    "frame": "task",
    "hidden": "false"
  },
  "criteria": {
    "soulrose": {
      "trigger": "minecraft:inventory_changed",
      "conditions": {
        "items": [
          {
            "items": [
              "wilder_horizons:faded_soul_rose",
              "wilder_horizons:soul_rose",
              "wilder_horizons:blue_soul_rose",
              "minecraft:wither_rose"
            ]
          }
        ]
      }
    }
  },
  "requirements": [
    [
      "soulrose"
    ]
  ]
}
